ramanspy/__init__.py
ramanspy/core.py
ramanspy/datasets.py
ramanspy/load.py
ramanspy/metrics.py
ramanspy/utils.py
ramanspy/analysis/Step.py
ramanspy/analysis/__init__.py
ramanspy/analysis/cluster.py
ramanspy/analysis/decompose.py
ramanspy/analysis/unmix.py
ramanspy/plot/__init__.py
ramanspy/plot/_core.py
ramanspy/plot/plot.py
ramanspy/preprocessing/Pipeline.py
ramanspy/preprocessing/Step.py
ramanspy/preprocessing/__init__.py
ramanspy/preprocessing/baseline.py
ramanspy/preprocessing/denoise.py
ramanspy/preprocessing/despike.py
ramanspy/preprocessing/misc.py
ramanspy/preprocessing/normalise.py
ramanspy/preprocessing/protocols.py
ramanspy/synth/__init__.py
ramanspy/synth/synth.py
ramanspy-0.2.9.dist-info/LICENSE
ramanspy-0.2.9.dist-info/METADATA
ramanspy-0.2.9.dist-info/WHEEL
ramanspy-0.2.9.dist-info/top_level.txt
ramanspy-0.2.9.dist-info/RECORD
