Metadata-Version: 2.1
Name: ramanspy
Version: 0.2.9
Summary: RamanSPy: An open-source Python package for integrative Raman spectroscopy data analysis
Author-email: Dimitar Georgiev <d.georgiev21@imperial.ac.uk>
License: BSD 3-Clause License
Project-URL: Documentation, https://ramanspy.readthedocs.io
Project-URL: Source, https://github.com/barahona-research-group/RamanSPy
Project-URL: Preprint, https://chemrxiv.org/engage/chemrxiv/article-details/64a53861ba3e99daef8c9c51
Keywords: Raman spectroscopy,spectral analysis,chemometrics,preprocessing pipeline,artificial intelligence,machine learning,Python package
Classifier: License :: OSI Approved :: BSD License
Classifier: Programming Language :: Python
Classifier: Programming Language :: Python :: 3
Requires-Python: >=3.8
License-File: LICENSE
Requires-Dist: numpy
Requires-Dist: matplotlib
Requires-Dist: scipy
Requires-Dist: scikit-learn
Requires-Dist: pybaselines
Requires-Dist: pysptools
Requires-Dist: cvxopt
Requires-Dist: renishawWiRE
Requires-Dist: pandas
Requires-Dist: wget
